card_management_sdk-2.0.0.dist-info/licenses/LICENSE
shellcardmanagementapis/__init__.py
shellcardmanagementapis/api_helper.py
shellcardmanagementapis/configuration.py
shellcardmanagementapis/shellcardmanagementapis_client.py
shellcardmanagementapis/controllers/__init__.py
shellcardmanagementapis/controllers/base_controller.py
shellcardmanagementapis/controllers/card_controller.py
shellcardmanagementapis/controllers/customer_controller.py
shellcardmanagementapis/controllers/o_auth_authorization_controller.py
shellcardmanagementapis/controllers/restriction_controller.py
shellcardmanagementapis/exceptions/__init__.py
shellcardmanagementapis/exceptions/api_exception.py
shellcardmanagementapis/exceptions/error_object_error_exception.py
shellcardmanagementapis/exceptions/o_auth_provider_exception.py
shellcardmanagementapis/http/__init__.py
shellcardmanagementapis/http/http_call_back.py
shellcardmanagementapis/http/http_method_enum.py
shellcardmanagementapis/http/http_request.py
shellcardmanagementapis/http/http_response.py
shellcardmanagementapis/http/auth/__init__.py
shellcardmanagementapis/http/auth/o_auth_2.py
shellcardmanagementapis/models/__init__.py
shellcardmanagementapis/models/account_access.py
shellcardmanagementapis/models/account_req.py
shellcardmanagementapis/models/account_request.py
shellcardmanagementapis/models/account_res.py
shellcardmanagementapis/models/account_response_accounts_items.py
shellcardmanagementapis/models/account_restriction_request.py
shellcardmanagementapis/models/account_restriction_res.py
shellcardmanagementapis/models/account_restriction_response.py
shellcardmanagementapis/models/account_velocity_limit.py
shellcardmanagementapis/models/accounts.py
shellcardmanagementapis/models/address.py
shellcardmanagementapis/models/audit_array_elements.py
shellcardmanagementapis/models/audit_req.py
shellcardmanagementapis/models/audit_request.py
shellcardmanagementapis/models/audit_response.py
shellcardmanagementapis/models/audit_response_audits_items.py
card_management_sdk-2.0.0.dist-info/METADATA
card_management_sdk-2.0.0.dist-info/WHEEL
card_management_sdk-2.0.0.dist-info/top_level.txt
card_management_sdk-2.0.0.dist-info/RECORD
