Metadata-Version: 2.4
Name: card-management-sdk
Version: 2.0.0
Summary: The Shell Card Management API is REST-based and employs OAUTH 2.0,Basic and ApiKey authentication. The API endpoints accept JSON-encoded request bodies, return JSON-encoded responses and use standard HTTP response codes.
Author-email: developer sdksio <developer+sdksio@apimatic.io>
Project-URL: Documentation, https://developer.shell.com/product-catalog/shell-card-management-advanced/sdk
Keywords: Shell,Card Management,APIMatic,SDKs
Requires-Python: >=3.7
License-File: LICENSE
Requires-Dist: apimatic-core>=0.2.20,~=0.2.0
Requires-Dist: apimatic-core-interfaces>=0.1.5,~=0.1.0
Requires-Dist: apimatic-requests-client-adapter>=0.1.6,~=0.1.0
Provides-Extra: testutils
Requires-Dist: pytest>=7.2.2; extra == "testutils"
Dynamic: license-file
